crum/__init__.py
crum/signals.py
django_crum-0.7.8.dist-info/LICENSE
django_crum-0.7.8.dist-info/METADATA
django_crum-0.7.8.dist-info/WHEEL
django_crum-0.7.8.dist-info/top_level.txt
django_crum-0.7.8.dist-info/RECORD
