Metadata-Version: 2.1
Name: django-crum
Version: 0.7.8
Summary: Django middleware to capture current request and user.
Home-page: https://github.com/ninemoreminutes/django-crum/
Author: Nine More Minutes, Inc.
Author-email: support@ninemoreminutes.com
License: BSD
Project-URL: Documentation, https://django-crum.rtfd.org/
Project-URL: Source, https://github.com/ninemoreminutes/django-crum/
Project-URL: Tracker, https://github.com/ninemoreminutes/django-crum/issues
Keywords: django,request,user,middleware,thread,local
Platform: UNKNOWN
Classifier: Development Status :: 4 - Beta
Classifier: Environment :: Web Environment
Classifier: Framework :: Django
Classifier: Framework :: Django :: 1.11
Classifier: Framework :: Django :: 2.0
Classifier: Framework :: Django :: 2.1
Classifier: Framework :: Django :: 2.2
Classifier: Framework :: Django :: 3.0
Classifier: Framework :: Django :: 3.1
Classifier: Intended Audience :: Developers
Classifier: License :: OSI Approved :: BSD License
Classifier: Operating System :: OS Independent
Classifier: Programming Language :: Python
Classifier: Programming Language :: Python :: 3
Classifier: Programming Language :: Python :: 3.4
Classifier: Programming Language :: Python :: 3.5
Classifier: Programming Language :: Python :: 3.6
Classifier: Programming Language :: Python :: 3.7
Classifier: Programming Language :: Python :: 3.8
Classifier: Programming Language :: Python :: 3.9
Classifier: Topic :: Internet :: WWW/HTTP
Classifier: Topic :: Software Development :: Libraries
Classifier: Topic :: Software Development :: Libraries :: Python Modules
Requires-Dist: django (>=1.8)
